cellestial/__init__.py
cellestial/_version.py
cellestial/docs/__init__.py
cellestial/docs/docstrings.py
cellestial/frames/__init__.py
cellestial/frames/construct.py
cellestial/single/__init__.py
cellestial/single/basic/__init__.py
cellestial/single/basic/scatter.py
cellestial/single/core/__init__.py
cellestial/single/core/dimensional.py
cellestial/single/core/distribution.py
cellestial/single/core/grids.py
cellestial/single/core/subdimensional.py
cellestial/single/special/__init__.py
cellestial/single/special/dotplot.py
cellestial/themes/__init__.py
cellestial/themes/_scatters.py
cellestial/themes/_violins.py
cellestial/util/__init__.py
cellestial/util/colors.py
cellestial/util/decorators.py
cellestial/util/errors.py
cellestial/util/utilities.py
cellestial-0.7.1.dist-info/LICENSE
cellestial-0.7.1.dist-info/METADATA
cellestial-0.7.1.dist-info/WHEEL
cellestial-0.7.1.dist-info/RECORD
