Metadata-Version: 2.3
Name: cellestial
Version: 0.7.1
Summary: 
License: Apache-2.0
Author: Zaf4
Author-email: zafermolbio@gmail.com
Requires-Python: >=3.10,<4.0
Classifier: License :: OSI Approved :: Apache Software License
Classifier: Programming Language :: Python :: 3
Classifier: Programming Language :: Python :: 3.10
Classifier: Programming Language :: Python :: 3.11
Classifier: Programming Language :: Python :: 3.12
Classifier: Programming Language :: Python :: 3.13
Requires-Dist: anndata (>=0.11.0,<0.12.0)
Requires-Dist: lets-plot (>=4.5.1,<5.0.0)
Requires-Dist: polars (==1.12.0)
Requires-Dist: pyarrow (>=18.0.0,<19.0.0)
